biomcp/__init__.py
biomcp/__main__.py
biomcp/cbioportal_helper.py
biomcp/circuit_breaker.py
biomcp/connection_pool.py
biomcp/constants.py
biomcp/core.py
biomcp/domain_handlers.py
biomcp/exceptions.py
biomcp/http_client.py
biomcp/http_client_simple.py
biomcp/individual_tools.py
biomcp/logging_filter.py
biomcp/metrics.py
biomcp/metrics_handler.py
biomcp/oncokb_helper.py
biomcp/parameter_parser.py
biomcp/prefetch.py
biomcp/query_parser.py
biomcp/query_router.py
biomcp/rate_limiter.py
biomcp/render.py
biomcp/request_batcher.py
biomcp/retry.py
biomcp/router.py
biomcp/router_handlers.py
biomcp/shared_context.py
biomcp/thinking_tool.py
biomcp/thinking_tracker.py
biomcp/articles/__init__.py
biomcp/articles/autocomplete.py
biomcp/articles/fetch.py
biomcp/articles/preprints.py
biomcp/articles/search.py
biomcp/articles/search_optimized.py
biomcp/articles/unified.py
biomcp/biomarkers/__init__.py
biomcp/biomarkers/search.py
biomcp/cli/__init__.py
biomcp/cli/articles.py
biomcp/cli/biomarkers.py
biomcp/cli/diseases.py
biomcp/cli/health.py
biomcp/cli/interventions.py
biomcp/cli/main.py
biomcp/cli/openfda.py
biomcp/cli/organizations.py
biomcp/cli/server.py
biomcp/cli/trials.py
biomcp/cli/variants.py
biomcp/diseases/__init__.py
biomcp/diseases/getter.py
biomcp/diseases/search.py
biomcp/drugs/__init__.py
biomcp/drugs/getter.py
biomcp/genes/__init__.py
biomcp/genes/getter.py
biomcp/integrations/__init__.py
biomcp/integrations/biothings_client.py
biomcp/integrations/cts_api.py
biomcp/interventions/__init__.py
biomcp/interventions/getter.py
biomcp/interventions/search.py
biomcp/openfda/__init__.py
biomcp/openfda/adverse_events.py
biomcp/openfda/adverse_events_helpers.py
biomcp/openfda/cache.py
biomcp/openfda/constants.py
biomcp/openfda/device_events.py
biomcp/openfda/device_events_helpers.py
biomcp/openfda/drug_approvals.py
biomcp/openfda/drug_labels.py
biomcp/openfda/drug_labels_helpers.py
biomcp/openfda/drug_recalls.py
biomcp/openfda/drug_recalls_helpers.py
iflow_mcp_biomcp_python-0.4.7.dist-info/licenses/LICENSE
iflow_mcp_biomcp_python-0.4.7.dist-info/METADATA
iflow_mcp_biomcp_python-0.4.7.dist-info/WHEEL
iflow_mcp_biomcp_python-0.4.7.dist-info/entry_points.txt
iflow_mcp_biomcp_python-0.4.7.dist-info/top_level.txt
iflow_mcp_biomcp_python-0.4.7.dist-info/RECORD
